<manifest alg="2" build="1176" opt="true" iceEnabled="true" iceMarkupVersion="2" exportTarget="other" resolutions="1x,2x" timestamp="1463951049567">
  <folder name="css">
    <file name="site_global.css" crc="4008894268"/>
    <file name="master_a-__.css" crc="133670571" ref="vision:module-db520:module-db118:index:growth:project-dph96:goals:module-db305:past"/>
    <file name="vision.css" crc="3964640084" ref="vision"/>
    <file name="module-db520.css" crc="4217821505" ref="module-db520"/>
    <file name="module-db118.css" crc="3940336881" ref="module-db118"/>
    <file name="index.css" crc="174439761" ref="index"/>
    <file name="growth.css" crc="4209933373" ref="growth"/>
    <file name="project-dph96.css" crc="3846350819" ref="project-dph96"/>
    <file name="goals.css" crc="4194846896" ref="goals"/>
    <file name="module-db305.css" crc="4250644602" ref="module-db305"/>
    <file name="past.css" crc="3867064575" ref="past"/>
  </folder>
  <folder name="scripts">
    <file name="jquery-1.8.3.min.js" crc="221936890" ref="index:vision:goals:module-db118:growth:past:module-db520:project-dph96:module-db305"/>
    <file name="museutils.js" crc="3793461109" ref="index:vision:goals:module-db118:growth:past:module-db520:project-dph96:module-db305"/>
    <file name="pie.js" crc="3827607177" ref="index:vision:goals:module-db118:growth:past:module-db520:project-dph96:module-db305"/>
    <file name="webpro.js" crc="4263367560" ref="index:vision:goals:module-db118:growth:past:module-db520:project-dph96:module-db305"/>
    <file name="musewpdisclosure.js" crc="513264147" ref="index:vision:goals:module-db118:growth:past:module-db520:project-dph96:module-db305"/>
    <file name="jquery.watch.js" crc="3766403489" ref="index:vision:goals:module-db118:growth:past:module-db520:project-dph96:module-db305"/>
  </folder>
  <folder name="images">
    <file name="u158-4.png" crc="118210892" ref="index:vision:goals:module-db118:growth:past:module-db520:project-dph96:module-db305"/>
    <file name="u158-4_2x.png" crc="420641097" ref="index:vision:goals:module-db118:growth:past:module-db520:project-dph96:module-db305"/>
    <file name="u355-4.png" crc="4066155156" ref="index:vision:goals:module-db118:growth:past:module-db520:project-dph96:module-db305"/>
    <file name="u355-4_2x.png" crc="403727123" ref="index:vision:goals:module-db118:growth:past:module-db520:project-dph96:module-db305"/>
    <file name="44pic_hd1-crop-u317.jpg" crc="107422355" ref="index"/>
    <file name="44pic_hd1-crop-u317_2x.jpg" crc="195562518" ref="index"/>
    <file name="u313-12.png" crc="245975975" ref="index"/>
    <file name="u313-12_2x.png" crc="3763345520" ref="index"/>
    <file name="fill 5-u332.png" crc="4024791926" ref="index"/>
    <file name="fill 5-u332_2x.png" crc="413052357" ref="index"/>
    <file name="u410-4.png" crc="530873247" ref="vision"/>
    <file name="u410-4_2x.png" crc="329478069" ref="vision"/>
    <file name="u706-4.png" crc="86308542" ref="vision"/>
    <file name="u706-4_2x.png" crc="482733662" ref="vision"/>
    <file name="u356-6.png" crc="15352756" ref="vision"/>
    <file name="u356-6_2x.png" crc="419849627" ref="vision"/>
    <file name="u378-6.png" crc="217095134" ref="vision"/>
    <file name="u378-6_2x.png" crc="23501777" ref="vision"/>
    <file name="u1765-4.png" crc="4090091673" ref="vision"/>
    <file name="u1765-4_2x.png" crc="255307261" ref="vision"/>
    <file name="u1764-4.png" crc="189564825" ref="vision"/>
    <file name="u1764-4_2x.png" crc="183776474" ref="vision"/>
    <file name="fill 5-u357.png" crc="4024791926" ref="vision"/>
    <file name="fill 5-u357_2x.png" crc="413052357" ref="vision"/>
    <file name="u885-4.png" crc="241283069" ref="goals"/>
    <file name="u885-4_2x.png" crc="432364126" ref="goals"/>
    <file name="u426-26.png" crc="3820668186" ref="goals"/>
    <file name="u426-26_2x.png" crc="144878082" ref="goals"/>
    <file name="u431-31.png" crc="4068335577" ref="goals"/>
    <file name="u431-31_2x.png" crc="235075145" ref="goals"/>
    <file name="u971-24.png" crc="4264895224" ref="goals"/>
    <file name="u971-24_2x.png" crc="3939411380" ref="goals"/>
    <file name="u972-21.png" crc="416981857" ref="goals"/>
    <file name="u972-21_2x.png" crc="3867440109" ref="goals"/>
    <file name="u973-21.png" crc="366506104" ref="goals"/>
    <file name="u973-21_2x.png" crc="3814258555" ref="goals"/>
    <file name="fill 5-u423.png" crc="4024791926" ref="goals"/>
    <file name="fill 5-u423_2x.png" crc="413052357" ref="goals"/>
    <file name="u977-4.png" crc="370914758" ref="module-db118"/>
    <file name="u977-4_2x.png" crc="457817841" ref="module-db118"/>
    <file name="u980-6.png" crc="274014548" ref="module-db118"/>
    <file name="u980-6_2x.png" crc="139006218" ref="module-db118"/>
    <file name="u1777-4.png" crc="473485605" ref="module-db118"/>
    <file name="u1777-4_2x.png" crc="3825592865" ref="module-db118"/>
    <file name="u1778-4.png" crc="103275056" ref="module-db118"/>
    <file name="u1778-4_2x.png" crc="4076429776" ref="module-db118"/>
    <file name="u989-5.png" crc="3795169636" ref="module-db118"/>
    <file name="u989-5_2x.png" crc="308111077" ref="module-db118"/>
    <file name="u991-5.png" crc="4230325265" ref="module-db118"/>
    <file name="u991-5_2x.png" crc="3835357463" ref="module-db118"/>
    <file name="u1350-4.png" crc="489160031" ref="module-db118"/>
    <file name="u1350-4_2x.png" crc="497317283" ref="module-db118"/>
    <file name="u458-6.png" crc="44086451" ref="module-db118"/>
    <file name="u458-6_2x.png" crc="3856294324" ref="module-db118"/>
    <file name="u1348-6.png" crc="242724883" ref="module-db118"/>
    <file name="u1348-6_2x.png" crc="398917513" ref="module-db118"/>
    <file name="u1349-6.png" crc="3932845261" ref="module-db118"/>
    <file name="u1349-6_2x.png" crc="130930907" ref="module-db118"/>
    <file name="_aoo9769-crop-u1016.jpg" crc="3804417333" ref="module-db118"/>
    <file name="_aoo9769-crop-u1016_2x.jpg" crc="532533683" ref="module-db118"/>
    <file name="dsc_3742-crop-u1236.jpg" crc="4181863936" ref="module-db118"/>
    <file name="dsc_3742-crop-u1236_2x.jpg" crc="25133963" ref="module-db118"/>
    <file name="_aoo9780-crop-u1223.jpg" crc="162416941" ref="module-db118"/>
    <file name="_aoo9780-crop-u1223_2x.jpg" crc="515605845" ref="module-db118"/>
    <file name="img_1369-crop-u1257.jpg" crc="3978396385" ref="module-db118"/>
    <file name="img_1369-crop-u1257_2x.jpg" crc="4152206071" ref="module-db118"/>
    <file name="img_1370-crop-u1260.jpg" crc="445193075" ref="module-db118"/>
    <file name="img_1370-crop-u1260_2x.jpg" crc="121473934" ref="module-db118"/>
    <file name="img_1302-crop-u1233.jpg" crc="4188153100" ref="module-db118"/>
    <file name="img_1302-crop-u1233_2x.jpg" crc="4028754564" ref="module-db118"/>
    <file name="u459-10.png" crc="4192787067" ref="module-db118"/>
    <file name="u459-10_2x.png" crc="4017644866" ref="module-db118"/>
    <file name="u460-4.png" crc="4085540084" ref="module-db118"/>
    <file name="u460-4_2x.png" crc="213013734" ref="module-db118"/>
    <file name="u1352-4.png" crc="4164545634" ref="module-db118"/>
    <file name="u1352-4_2x.png" crc="3868139581" ref="module-db118"/>
    <file name="u1353-4.png" crc="67861500" ref="module-db118"/>
    <file name="u1353-4_2x.png" crc="3799594584" ref="module-db118"/>
    <file name="u1354-4.png" crc="3949303602" ref="module-db118"/>
    <file name="u1354-4_2x.png" crc="523457526" ref="module-db118"/>
    <file name="fill 5-u449.png" crc="4024791926" ref="module-db118"/>
    <file name="fill 5-u449_2x.png" crc="413052357" ref="module-db118"/>
    <file name="u1767-4.png" crc="3868701932" ref="growth"/>
    <file name="u1767-4_2x.png" crc="4008243882" ref="growth"/>
    <file name="u1785-4.png" crc="4048572482" ref="growth"/>
    <file name="u1785-4_2x.png" crc="434895762" ref="growth"/>
    <file name="u1786-4.png" crc="50835163" ref="growth"/>
    <file name="u1786-4_2x.png" crc="3896490431" ref="growth"/>
    <file name="u2000-4.png" crc="432662046" ref="growth"/>
    <file name="u2000-4_2x.png" crc="3962096992" ref="growth"/>
    <file name="u2033-4.png" crc="239396557" ref="growth"/>
    <file name="u2033-4_2x.png" crc="4293357644" ref="growth"/>
    <file name="u2035-4.png" crc="204145417" ref="growth"/>
    <file name="u2035-4_2x.png" crc="451348986" ref="growth"/>
    <file name="u2031-4.png" crc="3934777163" ref="growth"/>
    <file name="u2031-4_2x.png" crc="212842033" ref="growth"/>
    <file name="u2032-4.png" crc="301980596" ref="growth"/>
    <file name="u2032-4_2x.png" crc="535128275" ref="growth"/>
    <file name="u2034-4.png" crc="4216419943" ref="growth"/>
    <file name="u2034-4_2x.png" crc="3894327790" ref="growth"/>
    <file name="blank.gif" crc="4208392903" ref="growth"/>
    <file name="u1836.png" crc="473138094" ref="growth"/>
    <file name="u1836-m.png" crc="473138094" ref="growth"/>
    <file name="u1836_2x.png" crc="376358865" ref="growth"/>
    <file name="u1836-m_2x.png" crc="376358865" ref="growth"/>
    <file name="u2047-4.png" crc="3766042936" ref="growth"/>
    <file name="u2047-4_2x.png" crc="508166534" ref="growth"/>
    <file name="u1844.png" crc="276485629" ref="growth"/>
    <file name="u1844-m.png" crc="276485629" ref="growth"/>
    <file name="u1844_2x.png" crc="4117355599" ref="growth"/>
    <file name="u1844-m_2x.png" crc="4117355599" ref="growth"/>
    <file name="u2048-4.png" crc="409834967" ref="growth"/>
    <file name="u2048-4_2x.png" crc="462211048" ref="growth"/>
    <file name="u1874.png" crc="4030554855" ref="growth"/>
    <file name="u1874-m.png" crc="4030554855" ref="growth"/>
    <file name="u1874_2x.png" crc="4085127664" ref="growth"/>
    <file name="u1874-m_2x.png" crc="4085127664" ref="growth"/>
    <file name="u2050-4.png" crc="3803646779" ref="growth"/>
    <file name="u2050-4_2x.png" crc="431880927" ref="growth"/>
    <file name="u1878.png" crc="187792883" ref="growth"/>
    <file name="u1878-m.png" crc="187792883" ref="growth"/>
    <file name="u1878_2x.png" crc="4216375142" ref="growth"/>
    <file name="u1878-m_2x.png" crc="4216375142" ref="growth"/>
    <file name="u2051-4.png" crc="291084547" ref="growth"/>
    <file name="u2051-4_2x.png" crc="3969550800" ref="growth"/>
    <file name="u1884.png" crc="73095758" ref="growth"/>
    <file name="u1884-m.png" crc="73095758" ref="growth"/>
    <file name="u1884_2x.png" crc="422394956" ref="growth"/>
    <file name="u1884-m_2x.png" crc="422394956" ref="growth"/>
    <file name="u2054-4.png" crc="4230236508" ref="growth"/>
    <file name="u2054-4_2x.png" crc="311970843" ref="growth"/>
    <file name="u1881.png" crc="417873050" ref="growth"/>
    <file name="u1881-m.png" crc="417873050" ref="growth"/>
    <file name="u1881_2x.png" crc="3781293669" ref="growth"/>
    <file name="u1881-m_2x.png" crc="3781293669" ref="growth"/>
    <file name="u2052-4.png" crc="3783179723" ref="growth"/>
    <file name="u2052-4_2x.png" crc="3922849181" ref="growth"/>
    <file name="u1886.png" crc="304087310" ref="growth"/>
    <file name="u1886-m.png" crc="304087310" ref="growth"/>
    <file name="u1886_2x.png" crc="4081554471" ref="growth"/>
    <file name="u1886-m_2x.png" crc="4081554471" ref="growth"/>
    <file name="u2055-4.png" crc="275172074" ref="growth"/>
    <file name="u2055-4_2x.png" crc="4139249677" ref="growth"/>
    <file name="u1889.png" crc="4144762720" ref="growth"/>
    <file name="u1889-m.png" crc="4144762720" ref="growth"/>
    <file name="u1889_2x.png" crc="412920745" ref="growth"/>
    <file name="u1889-m_2x.png" crc="412920745" ref="growth"/>
    <file name="u2056-4.png" crc="37050944" ref="growth"/>
    <file name="u2056-4_2x.png" crc="4282112346" ref="growth"/>
    <file name="u1893.png" crc="453397993" ref="growth"/>
    <file name="u1893-m.png" crc="453397993" ref="growth"/>
    <file name="u1893_2x.png" crc="503433646" ref="growth"/>
    <file name="u1893-m_2x.png" crc="503433646" ref="growth"/>
    <file name="u2058-4.png" crc="4194297796" ref="growth"/>
    <file name="u2058-4_2x.png" crc="4163343928" ref="growth"/>
    <file name="u1895.png" crc="48854847" ref="growth"/>
    <file name="u1895-m.png" crc="48854847" ref="growth"/>
    <file name="u1895_2x.png" crc="441000901" ref="growth"/>
    <file name="u1895-m_2x.png" crc="441000901" ref="growth"/>
    <file name="u2060-4.png" crc="369450392" ref="growth"/>
    <file name="u2060-4_2x.png" crc="4235674755" ref="growth"/>
    <file name="u1769-9.png" crc="3913101878" ref="growth"/>
    <file name="u1769-9_2x.png" crc="404528033" ref="growth"/>
    <file name="u1770-5.png" crc="3807830847" ref="growth"/>
    <file name="u1770-5_2x.png" crc="367431586" ref="growth"/>
    <file name="屏幕快照 2015-06-23 141002.jpg" crc="514537120" ref="growth"/>
    <file name="屏幕快照 2015-06-23 141002_2x.jpg" crc="169716148" ref="growth"/>
    <file name="屏幕快照 2015-06-23 141031.jpg" crc="3997819280" ref="growth"/>
    <file name="屏幕快照 2015-06-23 141031_2x.jpg" crc="81387800" ref="growth"/>
    <file name="屏幕快照 2015-06-23 140901-crop-u1801.jpg" crc="3810838163" ref="growth"/>
    <file name="屏幕快照 2015-06-23 140901-crop-u1801_2x.jpg" crc="333026356" ref="growth"/>
    <file name="u1815-6.png" crc="267163277" ref="growth"/>
    <file name="u1815-6_2x.png" crc="4006552475" ref="growth"/>
    <file name="屏幕快照 2015-06-23 141720.jpg" crc="154884006" ref="growth"/>
    <file name="屏幕快照 2015-06-23 141720_2x.jpg" crc="3787589199" ref="growth"/>
    <file name="屏幕快照 2015-06-23 141702-crop-u1819.jpg" crc="31542319" ref="growth"/>
    <file name="屏幕快照 2015-06-23 141702-crop-u1819_2x.jpg" crc="3899404574" ref="growth"/>
    <file name="u1831-6.png" crc="4217217688" ref="growth"/>
    <file name="u1831-6_2x.png" crc="429098089" ref="growth"/>
    <file name="u1772-4.png" crc="224187669" ref="growth"/>
    <file name="u1772-4_2x.png" crc="3989411716" ref="growth"/>
    <file name="u1788-4.png" crc="4154634930" ref="growth"/>
    <file name="u1788-4_2x.png" crc="4208300216" ref="growth"/>
    <file name="u1789-4.png" crc="513192282" ref="growth"/>
    <file name="u1789-4_2x.png" crc="213082841" ref="growth"/>
    <file name="u882-4.png" crc="4073279577" ref="past"/>
    <file name="u882-4_2x.png" crc="3265117" ref="past"/>
    <file name="u883-6.png" crc="4099217450" ref="past"/>
    <file name="u883-6_2x.png" crc="531725665" ref="past"/>
    <file name="u402-9.png" crc="482775437" ref="past"/>
    <file name="u402-9_2x.png" crc="78974734" ref="past"/>
    <file name="u408-6.png" crc="4240096493" ref="past"/>
    <file name="u408-6_2x.png" crc="3988333948" ref="past"/>
    <file name="u884-4.png" crc="3805233230" ref="past"/>
    <file name="u884-4_2x.png" crc="3759163438" ref="past"/>
    <file name="fill 5-u420.png" crc="4024791926" ref="past"/>
    <file name="fill 5-u420_2x.png" crc="413052357" ref="past"/>
    <file name="u1549-4.png" crc="370914758" ref="module-db520"/>
    <file name="u1549-4_2x.png" crc="457817841" ref="module-db520"/>
    <file name="u1550-4.png" crc="200043408" ref="module-db520"/>
    <file name="u1550-4_2x.png" crc="4055729239" ref="module-db520"/>
    <file name="u1783-4.png" crc="285689282" ref="module-db520"/>
    <file name="u1783-4_2x.png" crc="3863570196" ref="module-db520"/>
    <file name="u1784-4.png" crc="4140793824" ref="module-db520"/>
    <file name="u1784-4_2x.png" crc="318907762" ref="module-db520"/>
    <file name="u1553-4.png" crc="4167275840" ref="module-db520"/>
    <file name="u1553-4_2x.png" crc="4230431429" ref="module-db520"/>
    <file name="u1571-4.png" crc="489160031" ref="module-db520"/>
    <file name="u1571-4_2x.png" crc="497317283" ref="module-db520"/>
    <file name="u1544-6.png" crc="3778958150" ref="module-db520"/>
    <file name="u1544-6_2x.png" crc="3937498236" ref="module-db520"/>
    <file name="u1568-6.png" crc="488904528" ref="module-db520"/>
    <file name="u1568-6_2x.png" crc="4291769600" ref="module-db520"/>
    <file name="u1569-6.png" crc="4237154007" ref="module-db520"/>
    <file name="u1569-6_2x.png" crc="294753453" ref="module-db520"/>
    <file name="u1570-6.png" crc="284848448" ref="module-db520"/>
    <file name="u1570-6_2x.png" crc="4200319929" ref="module-db520"/>
    <file name="img_5935-crop-u1554.jpg" crc="4147245453" ref="module-db520"/>
    <file name="img_5935-crop-u1554_2x.jpg" crc="4233064578" ref="module-db520"/>
    <file name="img_5549-1-crop-u1558.jpg" crc="4262924753" ref="module-db520"/>
    <file name="img_5549-1-crop-u1558_2x.jpg" crc="4048468537" ref="module-db520"/>
    <file name="img_5985-crop-u1560.jpg" crc="224982402" ref="module-db520"/>
    <file name="img_5985-crop-u1560_2x.jpg" crc="3922836306" ref="module-db520"/>
    <file name="img_0531-crop-u1562.jpg" crc="411148723" ref="module-db520"/>
    <file name="img_0531-crop-u1562_2x.jpg" crc="399565563" ref="module-db520"/>
    <file name="img_0732-crop-u1556.jpg" crc="109935933" ref="module-db520"/>
    <file name="img_0732-crop-u1556_2x.jpg" crc="4263021577" ref="module-db520"/>
    <file name="img_0534-crop-u1564.jpg" crc="4116106319" ref="module-db520"/>
    <file name="img_0534-crop-u1564_2x.jpg" crc="411249725" ref="module-db520"/>
    <file name="u1545-12.png" crc="436858792" ref="module-db520"/>
    <file name="u1545-12_2x.png" crc="4294673723" ref="module-db520"/>
    <file name="u1546-4.png" crc="4085540084" ref="module-db520"/>
    <file name="u1546-4_2x.png" crc="213013734" ref="module-db520"/>
    <file name="u1572-4.png" crc="75440376" ref="module-db520"/>
    <file name="u1572-4_2x.png" crc="3890299391" ref="module-db520"/>
    <file name="u1573-4.png" crc="67861500" ref="module-db520"/>
    <file name="u1573-4_2x.png" crc="3799594584" ref="module-db520"/>
    <file name="u1583-4.png" crc="3811499066" ref="module-db520"/>
    <file name="u1583-4_2x.png" crc="4215842130" ref="module-db520"/>
    <file name="fill 5-u1522.png" crc="4024791926" ref="module-db520"/>
    <file name="fill 5-u1522_2x.png" crc="413052357" ref="module-db520"/>
    <file name="u1649-4.png" crc="4261061543" ref="project-dph96"/>
    <file name="u1649-4_2x.png" crc="4014539227" ref="project-dph96"/>
    <file name="u1650-4.png" crc="271216716" ref="project-dph96"/>
    <file name="u1650-4_2x.png" crc="3980693335" ref="project-dph96"/>
    <file name="u1643-4.png" crc="4166303922" ref="project-dph96"/>
    <file name="u1643-4_2x.png" crc="3994250331" ref="project-dph96"/>
    <file name="u1773-4.png" crc="4431868" ref="project-dph96"/>
    <file name="u1773-4_2x.png" crc="491472918" ref="project-dph96"/>
    <file name="u1653-4.png" crc="3970558989" ref="project-dph96"/>
    <file name="u1653-4_2x.png" crc="4040997595" ref="project-dph96"/>
    <file name="1.jpg" crc="4151412722" ref="project-dph96"/>
    <file name="1_2x.jpg" crc="385259321" ref="project-dph96"/>
    <file name="2.jpg" crc="3866233431" ref="project-dph96"/>
    <file name="2_2x.jpg" crc="318802380" ref="project-dph96"/>
    <file name="u1761-4.png" crc="3830222212" ref="project-dph96"/>
    <file name="u1761-4_2x.png" crc="273621625" ref="project-dph96"/>
    <file name="u1762-4.png" crc="3879928852" ref="project-dph96"/>
    <file name="u1762-4_2x.png" crc="417526608" ref="project-dph96"/>
    <file name="u1671-4.png" crc="489160031" ref="project-dph96"/>
    <file name="u1671-4_2x.png" crc="497317283" ref="project-dph96"/>
    <file name="u1644-6.png" crc="4230199787" ref="project-dph96"/>
    <file name="u1644-6_2x.png" crc="485107149" ref="project-dph96"/>
    <file name="u1668-6.png" crc="4291078715" ref="project-dph96"/>
    <file name="u1668-6_2x.png" crc="4076393122" ref="project-dph96"/>
    <file name="u1669-6.png" crc="4003513048" ref="project-dph96"/>
    <file name="u1669-6_2x.png" crc="3761910770" ref="project-dph96"/>
    <file name="u1670-6.png" crc="3874260333" ref="project-dph96"/>
    <file name="u1670-6_2x.png" crc="4193089791" ref="project-dph96"/>
    <file name="face3.jpg" crc="4196534021" ref="project-dph96"/>
    <file name="face3_2x.jpg" crc="4206725798" ref="project-dph96"/>
    <file name="dsc_4139-crop-u1658.jpg" crc="23591234" ref="project-dph96"/>
    <file name="dsc_4139-crop-u1658_2x.jpg" crc="366394160" ref="project-dph96"/>
    <file name="dsc_4146-crop-u1660.jpg" crc="125774467" ref="project-dph96"/>
    <file name="dsc_4146-crop-u1660_2x.jpg" crc="292125091" ref="project-dph96"/>
    <file name="img_2026-crop-u1662.jpg" crc="384219505" ref="project-dph96"/>
    <file name="img_2026-crop-u1662_2x.jpg" crc="93587107" ref="project-dph96"/>
    <file name="dscf8646-1-crop-u1725.jpg" crc="24394806" ref="project-dph96"/>
    <file name="dscf8646-1-crop-u1725_2x.jpg" crc="311590282" ref="project-dph96"/>
    <file name="7-1-crop-u1737.jpg" crc="431436475" ref="project-dph96"/>
    <file name="7-1-crop-u1737_2x.jpg" crc="435612237" ref="project-dph96"/>
    <file name="img_6263-crop-u1664.jpg" crc="389135793" ref="project-dph96"/>
    <file name="img_6263-crop-u1664_2x.jpg" crc="385063786" ref="project-dph96"/>
    <file name="img_5728-1-crop-u1728.jpg" crc="381129378" ref="project-dph96"/>
    <file name="img_5728-1-crop-u1728_2x.jpg" crc="343783813" ref="project-dph96"/>
    <file name="u1645-12.png" crc="2538405" ref="project-dph96"/>
    <file name="u1645-12_2x.png" crc="390172956" ref="project-dph96"/>
    <file name="u1646-4.png" crc="4090091673" ref="project-dph96"/>
    <file name="u1646-4_2x.png" crc="255307261" ref="project-dph96"/>
    <file name="u1673-4.png" crc="67861500" ref="project-dph96"/>
    <file name="u1673-4_2x.png" crc="3799594584" ref="project-dph96"/>
    <file name="u1674-4.png" crc="174398921" ref="project-dph96"/>
    <file name="u1674-4_2x.png" crc="188806810" ref="project-dph96"/>
    <file name="u1763-4.png" crc="200806692" ref="project-dph96"/>
    <file name="u1763-4_2x.png" crc="3777486511" ref="project-dph96"/>
    <file name="fill 5-u497.png" crc="4024791926" ref="project-dph96"/>
    <file name="fill 5-u497_2x.png" crc="413052357" ref="project-dph96"/>
    <file name="fill 5-u1641.png" crc="4024791926" ref="project-dph96"/>
    <file name="fill 5-u1641_2x.png" crc="413052357" ref="project-dph96"/>
    <file name="u1361-4.png" crc="370914758" ref="module-db305"/>
    <file name="u1361-4_2x.png" crc="457817841" ref="module-db305"/>
    <file name="u1362-4.png" crc="3820486316" ref="module-db305"/>
    <file name="u1362-4_2x.png" crc="4166775850" ref="module-db305"/>
    <file name="u1779-4.png" crc="4172850722" ref="module-db305"/>
    <file name="u1779-4_2x.png" crc="216872048" ref="module-db305"/>
    <file name="u1780-4.png" crc="277776828" ref="module-db305"/>
    <file name="u1780-4_2x.png" crc="69835627" ref="module-db305"/>
    <file name="u1367-4.png" crc="4167275840" ref="module-db305"/>
    <file name="u1367-4_2x.png" crc="4230431429" ref="module-db305"/>
    <file name="u1385-4.png" crc="489160031" ref="module-db305"/>
    <file name="u1385-4_2x.png" crc="497317283" ref="module-db305"/>
    <file name="u1356-6.png" crc="346442945" ref="module-db305"/>
    <file name="u1356-6_2x.png" crc="4050532081" ref="module-db305"/>
    <file name="u1383-6.png" crc="379657168" ref="module-db305"/>
    <file name="u1383-6_2x.png" crc="19564933" ref="module-db305"/>
    <file name="u1384-6.png" crc="3834080178" ref="module-db305"/>
    <file name="u1384-6_2x.png" crc="250358514" ref="module-db305"/>
    <file name="u1395-6.png" crc="268752669" ref="module-db305"/>
    <file name="u1395-6_2x.png" crc="439737238" ref="module-db305"/>
    <file name="4pic_hd-crop-u1369.jpg" crc="414699303" ref="module-db305"/>
    <file name="4pic_hd-crop-u1369_2x.jpg" crc="106530134" ref="module-db305"/>
    <file name="_aoo9826-crop-u1371.jpg" crc="4022017160" ref="module-db305"/>
    <file name="_aoo9826-crop-u1371_2x.jpg" crc="3776958194" ref="module-db305"/>
    <file name="6pic_hd-crop-u1375.jpg" crc="4275224103" ref="module-db305"/>
    <file name="6pic_hd-crop-u1375_2x.jpg" crc="401961121" ref="module-db305"/>
    <file name="2pic_hd-crop-u1379.jpg" crc="376258908" ref="module-db305"/>
    <file name="2pic_hd-crop-u1379_2x.jpg" crc="4070096619" ref="module-db305"/>
    <file name="img_1851-crop-u1373.jpg" crc="4221945590" ref="module-db305"/>
    <file name="img_1851-crop-u1373_2x.jpg" crc="3946553564" ref="module-db305"/>
    <file name="_aoo9820-2-crop-u1377.jpg" crc="3875877335" ref="module-db305"/>
    <file name="_aoo9820-2-crop-u1377_2x.jpg" crc="3782284280" ref="module-db305"/>
    <file name="u1357-12.png" crc="3998410894" ref="module-db305"/>
    <file name="u1357-12_2x.png" crc="136510992" ref="module-db305"/>
    <file name="u1358-4.png" crc="4085540084" ref="module-db305"/>
    <file name="u1358-4_2x.png" crc="213013734" ref="module-db305"/>
    <file name="u1386-4.png" crc="4164545634" ref="module-db305"/>
    <file name="u1386-4_2x.png" crc="3868139581" ref="module-db305"/>
    <file name="u1387-4.png" crc="67861500" ref="module-db305"/>
    <file name="u1387-4_2x.png" crc="3799594584" ref="module-db305"/>
    <file name="u1388-4.png" crc="174398921" ref="module-db305"/>
    <file name="u1388-4_2x.png" crc="3838535823" ref="module-db305"/>
    <file name="fill 5-u510.png" crc="4024791926" ref="module-db305"/>
    <file name="fill 5-u510_2x.png" crc="413052357" ref="module-db305"/>
  </folder>
  <file name="index.html" crc="4128297969" mt="1435085310923" redirect="true"/>
  <file name="vision.html" crc="439548458" mt="1435085889365" redirect="true"/>
  <file name="goals.html" crc="4063437377" mt="1435071378409" redirect="true"/>
  <file name="module-db118.html" crc="3933043594" mt="1435085629569" redirect="true"/>
  <file name="growth.html" crc="3804427441" mt="1435085661874" redirect="true"/>
  <file name="past.html" crc="42551725" mt="1435664229745" redirect="true"/>
  <file name="module-db520.html" crc="86176522" mt="1435085643874" redirect="true"/>
  <file name="project-dph96.html" crc="228855246" mt="1435663500418" redirect="true"/>
  <file name="module-db305.html" crc="347343997" mt="1435085778432" redirect="true"/>
</manifest>